{
    "required": false,
    "minVersion": "0.8",
    "priority": -69420,
    "mixinPriority": -69420,
    "verbose": true,
    "compatibilityLevel": "JAVA_8",
    "package": "dev.fastmc.allocfix.main",
    "client": [
        "MixinArrayVoxelShape",
        "MixinDirection",
        "MixinMinecraftClient",
        "MixinNbtCompound",
        "MixinSimpleVoxelShape",
        "MixinSlicedVoxelShape",
        "entity.MixinGoalSelector",
        "render.MixinBufferBuilder",
        "render.MixinBufferRenderer",
        "render.MixinDebugHud",
        "render.MixinEntityRenderer",
        "render.MixinFontStorage",
        "render.MixinFrustum",
        "render.MixinImmediate",
        "render.MixinModelPart",
        "render.MixinVertexConsumer",
        "render.MixinVertexConsumerImpls",
        "render.matrix.MixinMatrix3f",
        "render.matrix.MixinMatrix4f",
        "render.matrix.MixinMatrixStack",
        "render.terrain.MixinAmbientOcclusionCalculator",
        "render.terrain.MixinBlockModelRenderer",
        "render.terrain.MixinChunkRendererRegion",
        "render.terrain.MixinFluidRenderer",
        "render.terrain.MixinWorldRenderer",
        "world.MixinBlock",
        "world.MixinBlockView",
        "world.MixinChunkRendererRegion",
        "world.MixinClientWorld",
        "world.MixinEmptyChunk",
        "world.MixinFlowableFluid",
        "world.MixinRenderedChunk",
        "world.MixinWorld",
        "world.MixinWorldChunk"
    ]
}
